{"GridSize":{"X":9,"Y":2,"Z":3},"TileSize":{"X":1,"Y":1,"Z":1},"Values":[[[{"TileType":1,"ShapeId":-1},{"TileType":1,"ShapeId":-1},{"TileType":1,"ShapeId":-1}],[0,{"TileType":4,"ShapeId":-1},0]],[[{"TileType":1,"ShapeId":-1},{"TileType":1,"ShapeId":-1},{"TileType":1,"ShapeId":-1}],[{"TileType":7,"ShapeId":-1,"TargetGridPositions":[{"X":5,"Y":0,"Z":1}]},0,0]],[[0,0,0],[0,0,0]],[[0,0,0],[0,0,0]],[[0,0,0],[0,0,0]],[[0,{"TileType":9,"ShapeId":-1,"Path":[{"X":5,"Y":0,"Z":1},{"X":4,"Y":0,"Z":1},{"X":3,"Y":0,"Z":1},{"X":2,"Y":0,"Z":1}]},0],[0,0,0]],[[{"TileType":1,"ShapeId":-1},{"TileType":1,"ShapeId":-1},{"TileType":1,"ShapeId":-1}],[{"TileType":6,"ShapeId":-1,"Path":[{"X":6,"Y":1,"Z":0},{"X":7,"Y":1,"Z":0},{"X":8,"Y":1,"Z":0},{"X":8,"Y":1,"Z":1},{"X":8,"Y":1,"Z":2},{"X":7,"Y":1,"Z":2},{"X":6,"Y":1,"Z":2},{"X":6,"Y":1,"Z":1}]},0,0]],[[{"TileType":1,"ShapeId":-1},{"TileType":1,"ShapeId":-1},{"TileType":1,"ShapeId":-1}],[0,{"TileType":5,"ShapeId":-1},0]],[[{"TileType":1,"ShapeId":-1},{"TileType":1,"ShapeId":-1},{"TileType":1,"ShapeId":-1}],[0,0,0]]]}